asgi_dispatcher_middleware/__init__.py
asgi_dispatcher_middleware/_core.py
asgi_dispatcher_middleware/asgitypes.py
asgi_dispatcher_middleware/py.typed
asgi_dispatcher_middleware-1.0.0.dist-info/LICENSE
asgi_dispatcher_middleware-1.0.0.dist-info/WHEEL
asgi_dispatcher_middleware-1.0.0.dist-info/METADATA
asgi_dispatcher_middleware-1.0.0.dist-info/RECORD
