Metadata-Version: 2.1
Name: asgi-dispatcher-middleware
Version: 1.0.0
Summary: Middleware to Dispatch to multiple ASGI applications, extracted from hypercorn.
Home-page: https://github.com/graingert/asgi-dispatcher-middleware
License: UNKNOWN
Author: Thomas Grainger
Author-email: asgi-dispatcher-middleware@graingert.co.uk
Requires-Python: ~=3.6
Classifier: License :: OSI Approved :: MIT License
Requires-Dist: anyio~=2.0
Requires-Dist: typing_extensions ; python_version<'3.8'
Requires-Dist: pytest ; extra == "test"
Requires-Dist: pytest-cov ; extra == "test"
Requires-Dist: coverage>=5.3 ; extra == "test"
Requires-Dist: anyio[trio,curio] ; extra == "test"
Requires-Dist: mypy>=0.800 ; extra == "test"
Provides-Extra: test
